streamlit_keypress/__init__.py
streamlit_keypress/frontend.py
streamlit_keypress/component/__init__.py
streamlit_keypress/component/index.html
streamlit_keypress/component/index.js
streamlit_keypress/component/streamlit-component-lib.js
streamlit_keypress-0.1.0.dist-info/licenses/LICENSE
streamlit_keypress-0.1.0.dist-info/METADATA
streamlit_keypress-0.1.0.dist-info/WHEEL
streamlit_keypress-0.1.0.dist-info/top_level.txt
streamlit_keypress-0.1.0.dist-info/RECORD
