Metadata-Version: 2.4
Name: streamlit-keypress
Version: 0.1.0
Summary: A Streamlit component to capture keyboard events
Home-page: https://github.com/sud900/streamlit-keypress
Author: Sudarsan
Author-email: sudarsan900@gmail.com
Classifier: Programming Language :: Python :: 3
Classifier: License :: OSI Approved :: MIT License
Classifier: Operating System :: OS Independent
Requires-Python: >=3.6
License-File: LICENSE
Requires-Dist: streamlit>=1.0.0
Dynamic: author
Dynamic: author-email
Dynamic: classifier
Dynamic: description
Dynamic: description-content-type
Dynamic: home-page
Dynamic: license-file
Dynamic: requires-dist
Dynamic: requires-python
Dynamic: summary
